LICENSE
MANIFEST.in
README.rst
setup.py
bin/ngalerie
ngalerie/__init__.py
ngalerie.egg-info/PKG-INFO
ngalerie.egg-info/SOURCES.txt
ngalerie.egg-info/dependency_links.txt
ngalerie.egg-info/requires.txt
ngalerie.egg-info/top_level.txt