Metadata-Version: 1.0
Name: ngalerie
Version: 1.0.1
Summary: A tool to manage Camera pictures (Rotate, Resize, Rename using EXIF).
Home-page: http://bitbucket.org/natim/ngallery/overview
Author: Rémy HUBSCHER
Author-email: remy.hubscher@ionyse.com
License: UNKNOWN
Platform: UNKNOWN
Classifier: Development Status :: 5 - Production/Stable
Classifier: Environment :: Console
Classifier: License :: OSI Approved :: GNU General Public License (GPL)
Classifier: Operating System :: OS Independent
Classifier: Programming Language :: Python
Classifier: Topic :: Multimedia :: Graphics :: Editors
Classifier: Topic :: Software Development :: Libraries :: Python Modules
